LICENSE
MANIFEST.in
README.md
requirements-pypy.txt
requirements.txt
setup.py
exec/marc2bf
exec/marcbin2xml
exec/versa2ttl
lib/__init__.py
lib/isbnplus.py
lib/util.py
lib/version.py
lib/contrib/__init__.py
lib/contrib/datachefids.py
lib/contrib/xmlutil.py
lib/plugin/__init__.py
lib/plugin/labelizer.py
lib/plugin/linkreport.py
lib/reader/__init__.py
lib/reader/engine.py
lib/reader/marc.py
lib/reader/marcextra.py
lib/reader/marcpatterns.py
lib/reader/marcworkidpatterns.py
lib/reader/marcxml.py
lib/reader/util.py
lib/writer/__init__.py
lib/writer/exhibitexplorer.py
lib/writer/microxml.py
lib/writer/rdf.py
pybibframe.egg-info/PKG-INFO
pybibframe.egg-info/SOURCES.txt
pybibframe.egg-info/dependency_links.txt
pybibframe.egg-info/requires.txt
pybibframe.egg-info/top_level.txt
test/README.md
test/speedtest.py
test/test_alt_patterns.py
test/test_isbns.py
test/test_linkhash.py
test/test_marc_snippets1.py
test/test_marc_snippets2.py
test/test_marc_snippets3.py
test/test_use_cases.py
test/resource/700t.mrx
test/resource/GW_bf_test10.mrx
test/resource/README.md
test/resource/democonfig.json
test/resource/edition-instances.mrx
test/resource/egyptskulls.mrx
test/resource/gunslinger.mrx
test/resource/joycebcat-140613.mrx
test/resource/kford-holdings1.mrx
test/resource/lcc-u.mrx
test/resource/multiple-authlinks.mrx
test/resource/nlm-multiple-isbn.mrx
test/resource/pervomu.mrx
test/resource/princeton-holdings1.mrx
test/resource/stanford_rda_parens.mrx
test/resource/timathom-140716.mrx
test/resource/workrelations.mrx
test/resource/zweig-tiny.mrx
test/resource/zweig.mrx