Metadata-Version: 2.1
Name: pybibframe
Version: 1.1.2
Summary: ('Python tools for BIBFRAME (Bibliographic Framework), a Web-friendly framework for bibliographic descriptions in libraries, for example.',)
Home-page: http://zepheira.com/
Author: Uche Ogbuji
Author-email: uche@ogbuji.net
Maintainer: Zepheira
Maintainer-email: uche@zepheira.com
License: License :: OSI Approved :: Apache Software License
Platform: UNKNOWN
Classifier: Programming Language :: Python
Classifier: Programming Language :: Python :: 3
Classifier: Development Status :: 5 - Production/Stable
Classifier: Intended Audience :: Information Technology
Classifier: License :: OSI Approved :: Apache Software License
Classifier: Operating System :: OS Independent
Classifier: Topic :: Software Development :: Libraries :: Python Modules
Classifier: Topic :: Internet :: WWW/HTTP
Classifier: Topic :: Database
Classifier: Topic :: Scientific/Engineering :: Information Analysis
Classifier: Topic :: Text Processing :: Markup :: XML
Classifier: Topic :: Text Processing :: Indexing
Classifier: Topic :: Utilities
